jack_midi_recorder/__init__.py
jack_midi_recorder/qt.py
jack_midi_recorder-1.2.2.dist-info/LICENSE
jack_midi_recorder-1.2.2.dist-info/WHEEL
jack_midi_recorder-1.2.2.dist-info/METADATA
jack_midi_recorder-1.2.2.dist-info/RECORD
