Metadata-Version: 2.1
Name: jack_midi_recorder
Version: 1.2.2
Summary: Basic implementation of MIDI event recording / playback.
Author-email: Leon Dionne <ldionne@dridesign.sh.cn>
Classifier: License :: OSI Approved :: GNU General Public License v3 or later (GPLv3+)
Classifier: Programming Language :: Python
Classifier: Programming Language :: Python :: 3.10
Classifier: Topic :: Multimedia :: Sound/Audio :: Sound Synthesis
Classifier: Topic :: Multimedia :: Sound/Audio :: MIDI
Requires-Dist: JACK-Client
Requires-Dist: numpy
Requires-Dist: PyQt5 ; extra == "qt"
Project-URL: Home, https://github.com/Zen-Master-SoSo/jack_midi_recorder
Provides-Extra: qt
